betfairmarketvolumesclient/__init__.py
betfairmarketvolumesclient/client.py
betfairmarketvolumesclient/exceptions.py
betfairmarketvolumesclient/utils.py
betfairmarketvolumesclient/resources/__init__.py
betfairmarketvolumesclient/resources/baseresource.py
betfairmarketvolumesclient/resources/marketresource.py
tests/__init__.py
tests/conftest.py
tests/utils.py
tests/resources/__init__.py
tests/unit/__init__.py
tests/unit/test_client.py
tests/unit/test_utils.py
tests/unit/resource/__init__.py
tests/unit/resource/test_marketresource.py
betfairmarketvolumesclient-0.0.6.dist-info/METADATA
betfairmarketvolumesclient-0.0.6.dist-info/WHEEL
betfairmarketvolumesclient-0.0.6.dist-info/top_level.txt
betfairmarketvolumesclient-0.0.6.dist-info/RECORD
