Metadata-Version: 2.1
Name: betfairmarketvolumesclient
Version: 0.0.6
Summary: Simple file downloader for the betfair daily sp files.
Home-page: https://github.com/varneyo/betfairmarketvolumesclient
Author: Oliver Varney
Author-email: oliverashleyvarney@gmail.com
License: MIT
Keywords: core packages
Platform: UNKNOWN
Classifier: Development Status :: 3 - Alpha
Classifier: Topic :: Utilities
Classifier: License :: OSI Approved :: MIT License
Requires-Dist: pytest
Requires-Dist: pydantic
Requires-Dist: pandas
Requires-Dist: tenacity
